starburst_scheduler/__init__.py
starburst_scheduler/cli.py
starburst_scheduler/connector.py
starburst_scheduler/scheduler.py
tests/__init__.py
tests/test_connector.py
starburst_scheduler-0.1.10.dist-info/LICENSE
starburst_scheduler-0.1.10.dist-info/METADATA
starburst_scheduler-0.1.10.dist-info/WHEEL
starburst_scheduler-0.1.10.dist-info/entry_points.txt
starburst_scheduler-0.1.10.dist-info/top_level.txt
starburst_scheduler-0.1.10.dist-info/RECORD
