Metadata-Version: 2.1
Name: starburst-scheduler
Version: 0.1.10
Summary: A pip package to run and schedule SQL queries on Starburst Galaxy or Enterprise clusters.
Home-page: https://github.com/karranikhilreddy99/starburst_scheduler
Author: Nikhil Reddy Karra
Author-email: knikhilreddy99@gmail.com
License: MIT
Classifier: Programming Language :: Python :: 3
Classifier: Programming Language :: Python :: 3.9
Classifier: Programming Language :: Python :: 3.10
Classifier: Programming Language :: Python :: 3.11
Classifier: License :: OSI Approved :: MIT License
Classifier: Operating System :: OS Independent
Requires-Python: >=3.9
License-File: LICENSE
Requires-Dist: pystarburst>=0.1.1
Requires-Dist: trino>=0.305.0
Requires-Dist: schedule>=1.1.0
Requires-Dist: click>=8.0.0
